<?xml version="1.0" encoding="UTF-8"?>
<rowset>
	<row>

		<person id="654">
			<first>Charis</first>
			<last>Bob</last>
			<middle>H</middle>
		</person>
		<address id="9175">
			<street1>8850 Goldstar</street1>
			<street2></street2>
			<city id="66320">
				<label>Northampton</label>
				<geocode>
					<lat>92451251</lat>
					<long>76386983</long>
					<accuracy>1</accuracy>
					<id>7527569</id>
				</geocode>
			</city>
			<state id="42099">
				<label>ID</label>
				<geocode>
					<lat>91270301</lat>
					<long>22348927</long>
					<accuracy>5</accuracy>
					<id>71025989</id>
				</geocode>
			</state>
			<zip id="30503">
				<label>90212</label>
				<geocode>
					<lat>85322586</lat>
					<long>13446584</long>
					<accuracy>5</accuracy>
					<id>1995863</id>
				</geocode>
			</zip>
			<phone id="9508">
				<type>1</type>
				<label>home</label>
				<area>930</area>
				<prefix>563</prefix>
				<ex>7655</ex>
			</phone>

			<phone id="10345">
				<type>1</type>
				<label>home</label>
				<area>881</area>
				<prefix>23</prefix>
				<ex>5337</ex>
			</phone>

			<notes>are you hungry?</notes>
			<geocode>
				<lat>45292366</lat>
				<long>51253521</long>
				<accuracy>4</accuracy>
				<id>39123026</id>
			</geocode>
		</address>
		<phone id="83848">
			<type>1</type>
			<label>home</label>
			<area>467</area>
			<prefix>283</prefix>
			<ex>7353</ex>
		</phone>
		<email id="63575">
			<label>email</label>
			<address>Chris@test.com</address>
			<nic>me</nic>
		</email>
		<notes>are you hungry?</notes>
	</row>
	<row>

		<person id="633">
			<first>Guillermo</first>
			<last>Bill</last>
			<middle>C</middle>
		</person>
		<address id="4131">
			<street1>3785 Goldstar</street1>
			<street2></street2>
			<city id="63009">
				<label>San Francisco</label>
				<geocode>
					<lat>1102482</lat>
					<long>64823644</long>
					<accuracy>2</accuracy>
					<id>81187188</id>
				</geocode>
			</city>
			<state id="46314">
				<label>ND</label>
				<geocode>
					<lat>53184529</lat>
					<long>62585011</long>
					<accuracy>5</accuracy>
					<id>35372595</id>
				</geocode>
			</state>
			<zip id="49429">
				<label>01581</label>
				<geocode>
					<lat>63155889</lat>
					<long>74812094</long>
					<accuracy>6</accuracy>
					<id>63324390</id>
				</geocode>
			</zip>
			<phone id="35387">
				<type>0</type>
				<label>home</label>
				<area>890</area>
				<prefix>582</prefix>
				<ex>6617</ex>
			</phone>

			<phone id="99429">
				<type>0</type>
				<label>home</label>
				<area>771</area>
				<prefix>952</prefix>
				<ex>1665</ex>
			</phone>

			<notes>are you hungry?</notes>
			<geocode>
				<lat>89565299</lat>
				<long>22258715</long>
				<accuracy>1</accuracy>
				<id>74972553</id>
			</geocode>
		</address>
		<phone id="80260">
			<type>0</type>
			<label>home</label>
			<area>363</area>
			<prefix>297</prefix>
			<ex>8544</ex>
		</phone>
		<email id="5602">
			<label>email</label>
			<address>Eric@test.com</address>
			<nic>me</nic>
		</email>
		<notes>are you hungry?</notes>
	</row>
</rowset>
