<?xml version="1.0" encoding="UTF-8"?>
<rowset>
	<row>

		<person id="748">
			<first>Hank</first>
			<last>Bobby</last>
			<middle>H</middle>
		</person>
		<address id="4050">
			<street1>1648 4th Street</street1>
			<street2></street2>
			<city id="20089">
				<label>Milford</label>
				<geocode>
					<lat>70328677</lat>
					<long>44553066</long>
					<accuracy>0</accuracy>
					<id>46308953</id>
				</geocode>
			</city>
			<state id="45735">
				<label>NC</label>
				<geocode>
					<lat>59280321</lat>
					<long>41207817</long>
					<accuracy>0</accuracy>
					<id>9772048</id>
				</geocode>
			</state>
			<zip id="56141">
				<label>01067</label>
				<geocode>
					<lat>56438128</lat>
					<long>81947784</long>
					<accuracy>5</accuracy>
					<id>52792609</id>
				</geocode>
			</zip>
			<phone id="40265">
				<type>0</type>
				<label>home</label>
				<area>42</area>
				<prefix>165</prefix>
				<ex>3623</ex>
			</phone>

			<phone id="28882">
				<type>0</type>
				<label>home</label>
				<area>21</area>
				<prefix>66</prefix>
				<ex>4092</ex>
			</phone>

			<notes>are you hungry?</notes>
			<geocode>
				<lat>92075167</lat>
				<long>52027676</long>
				<accuracy>6</accuracy>
				<id>54356675</id>
			</geocode>
		</address>
		<phone id="13979">
			<type>0</type>
			<label>home</label>
			<area>484</area>
			<prefix>269</prefix>
			<ex>2806</ex>
		</phone>
		<email id="98842">
			<label>email</label>
			<address>Dionne@test.com</address>
			<nic>me</nic>
		</email>
		<notes>are you hungry?</notes>
	</row>
	<row>

		<person id="639">
			<first>Cherry</first>
			<last>Bob</last>
			<middle>D</middle>
		</person>
		<address id="2184">
			<street1>86 5th Street</street1>
			<street2></street2>
			<city id="76255">
				<label>Brookline</label>
				<geocode>
					<lat>61505184</lat>
					<long>99252132</long>
					<accuracy>2</accuracy>
					<id>38097052</id>
				</geocode>
			</city>
			<state id="70983">
				<label>FL</label>
				<geocode>
					<lat>54606940</lat>
					<long>13418526</long>
					<accuracy>4</accuracy>
					<id>80363397</id>
				</geocode>
			</state>
			<zip id="54762">
				<label>90211</label>
				<geocode>
					<lat>20643788</lat>
					<long>47588823</long>
					<accuracy>3</accuracy>
					<id>3131422</id>
				</geocode>
			</zip>
			<phone id="14018">
				<type>0</type>
				<label>home</label>
				<area>858</area>
				<prefix>278</prefix>
				<ex>718</ex>
			</phone>

			<phone id="28338">
				<type>1</type>
				<label>home</label>
				<area>465</area>
				<prefix>373</prefix>
				<ex>2987</ex>
			</phone>

			<notes>are you hungry?</notes>
			<geocode>
				<lat>52496627</lat>
				<long>37285464</long>
				<accuracy>2</accuracy>
				<id>85845032</id>
			</geocode>
		</address>
		<phone id="91257">
			<type>0</type>
			<label>home</label>
			<area>332</area>
			<prefix>756</prefix>
			<ex>4301</ex>
		</phone>
		<email id="14148">
			<label>email</label>
			<address>Howard@test.com</address>
			<nic>me</nic>
		</email>
		<notes>are you hungry?</notes>
	</row>
</rowset>
