<?xml version="1.0" encoding="UTF-8"?>
<rowset>
	<row>

		<person id="501">
			<first>Bob</first>
			<last>Ben</last>
			<middle>H</middle>
		</person>
		<address id="1296">
			<street1>2270 6th Street</street1>
			<street2></street2>
			<city id="77220">
				<label>Northampton</label>
				<geocode>
					<lat>68103588</lat>
					<long>93458457</long>
					<accuracy>6</accuracy>
					<id>81461105</id>
				</geocode>
			</city>
			<state id="29001">
				<label>MA</label>
				<geocode>
					<lat>51396860</lat>
					<long>20262198</long>
					<accuracy>3</accuracy>
					<id>50300658</id>
				</geocode>
			</state>
			<zip id="45473">
				<label>01584</label>
				<geocode>
					<lat>51229229</lat>
					<long>59277140</long>
					<accuracy>7</accuracy>
					<id>39710904</id>
				</geocode>
			</zip>
			<phone id="84791">
				<type>1</type>
				<label>home</label>
				<area>190</area>
				<prefix>757</prefix>
				<ex>2043</ex>
			</phone>

			<phone id="38621">
				<type>1</type>
				<label>home</label>
				<area>443</area>
				<prefix>843</prefix>
				<ex>7012</ex>
			</phone>

			<notes>are you hungry?</notes>
			<geocode>
				<lat>79688256</lat>
				<long>4264163</long>
				<accuracy>0</accuracy>
				<id>67970274</id>
			</geocode>
		</address>
		<phone id="44382">
			<type>0</type>
			<label>home</label>
			<area>553</area>
			<prefix>761</prefix>
			<ex>7249</ex>
		</phone>
		<email id="53407">
			<label>email</label>
			<address>Cane@test.com</address>
			<nic>me</nic>
		</email>
		<notes>are you hungry?</notes>
	</row>
	<row>

		<person id="589">
			<first>Hughe</first>
			<last>Howards</last>
			<middle>B</middle>
		</person>
		<address id="1399">
			<street1>5425 Broadway</street1>
			<street2></street2>
			<city id="68816">
				<label>Brooklyn</label>
				<geocode>
					<lat>77984457</lat>
					<long>23915140</long>
					<accuracy>0</accuracy>
					<id>87693785</id>
				</geocode>
			</city>
			<state id="68093">
				<label>AZ</label>
				<geocode>
					<lat>63308893</lat>
					<long>54851129</long>
					<accuracy>3</accuracy>
					<id>5665835</id>
				</geocode>
			</state>
			<zip id="70719">
				<label>01065</label>
				<geocode>
					<lat>77741354</lat>
					<long>33256814</long>
					<accuracy>8</accuracy>
					<id>88573972</id>
				</geocode>
			</zip>
			<phone id="44066">
				<type>0</type>
				<label>home</label>
				<area>851</area>
				<prefix>300</prefix>
				<ex>4731</ex>
			</phone>

			<phone id="13423">
				<type>1</type>
				<label>home</label>
				<area>168</area>
				<prefix>256</prefix>
				<ex>6501</ex>
			</phone>

			<notes>are you hungry?</notes>
			<geocode>
				<lat>7085761</lat>
				<long>3235436</long>
				<accuracy>4</accuracy>
				<id>81500513</id>
			</geocode>
		</address>
		<phone id="48763">
			<type>0</type>
			<label>home</label>
			<area>880</area>
			<prefix>773</prefix>
			<ex>2086</ex>
		</phone>
		<email id="41227">
			<label>email</label>
			<address>Danielle@test.com</address>
			<nic>me</nic>
		</email>
		<notes>are you hungry?</notes>
	</row>
</rowset>
