<?xml version="1.0" encoding="UTF-8"?>
<rowset>
	<row>

		<person id="944">
			<first>Dionysus</first>
			<last>Cadwell</last>
			<middle>A</middle>
		</person>
		<address id="5742">
			<street1>9626 Goldstar</street1>
			<street2></street2>
			<city id="38704">
				<label>Westboro</label>
				<geocode>
					<lat>88146735</lat>
					<long>33353854</long>
					<accuracy>2</accuracy>
					<id>74242880</id>
				</geocode>
			</city>
			<state id="63915">
				<label>WI</label>
				<geocode>
					<lat>8339334</lat>
					<long>90343298</long>
					<accuracy>0</accuracy>
					<id>86088933</id>
				</geocode>
			</state>
			<zip id="64692">
				<label>92510</label>
				<geocode>
					<lat>56714545</lat>
					<long>93526192</long>
					<accuracy>8</accuracy>
					<id>76946629</id>
				</geocode>
			</zip>
			<phone id="82013">
				<type>1</type>
				<label>home</label>
				<area>845</area>
				<prefix>376</prefix>
				<ex>8076</ex>
			</phone>

			<phone id="47004">
				<type>0</type>
				<label>home</label>
				<area>184</area>
				<prefix>350</prefix>
				<ex>5460</ex>
			</phone>

			<notes>are you hungry?</notes>
			<geocode>
				<lat>32725110</lat>
				<long>90612193</long>
				<accuracy>5</accuracy>
				<id>1228119</id>
			</geocode>
		</address>
		<phone id="83278">
			<type>1</type>
			<label>home</label>
			<area>550</area>
			<prefix>580</prefix>
			<ex>3959</ex>
		</phone>
		<email id="22245">
			<label>email</label>
			<address>Dartanion@test.com</address>
			<nic>me</nic>
		</email>
		<notes>are you hungry?</notes>
	</row>
	<row>

		<person id="343">
			<first>Guillermo</first>
			<last>DeCascos</last>
			<middle>D</middle>
		</person>
		<address id="5470">
			<street1>2716 Main Blvd</street1>
			<street2></street2>
			<city id="44966">
				<label>Hopkinton</label>
				<geocode>
					<lat>29749389</lat>
					<long>76402913</long>
					<accuracy>1</accuracy>
					<id>66991438</id>
				</geocode>
			</city>
			<state id="72889">
				<label>MI</label>
				<geocode>
					<lat>98009273</lat>
					<long>42384388</long>
					<accuracy>7</accuracy>
					<id>25070673</id>
				</geocode>
			</state>
			<zip id="73649">
				<label>01583</label>
				<geocode>
					<lat>8734170</lat>
					<long>80578234</long>
					<accuracy>2</accuracy>
					<id>68852434</id>
				</geocode>
			</zip>
			<phone id="55251">
				<type>0</type>
				<label>home</label>
				<area>289</area>
				<prefix>733</prefix>
				<ex>605</ex>
			</phone>

			<phone id="74634">
				<type>1</type>
				<label>home</label>
				<area>992</area>
				<prefix>844</prefix>
				<ex>5871</ex>
			</phone>

			<notes>are you hungry?</notes>
			<geocode>
				<lat>27652068</lat>
				<long>48671066</long>
				<accuracy>1</accuracy>
				<id>291010</id>
			</geocode>
		</address>
		<phone id="29992">
			<type>1</type>
			<label>home</label>
			<area>653</area>
			<prefix>85</prefix>
			<ex>8033</ex>
		</phone>
		<email id="18525">
			<label>email</label>
			<address>Candy@test.com</address>
			<nic>me</nic>
		</email>
		<notes>are you hungry?</notes>
	</row>
</rowset>
