<?xml version="1.0" encoding="UTF-8"?>
<rowset>
	<row>

		<person id="650">
			<first>Guillermo</first>
			<last>Arron</last>
			<middle>H</middle>
		</person>
		<address id="219">
			<street1>5804 Central</street1>
			<street2></street2>
			<city id="25814">
				<label>Santa Cruz</label>
				<geocode>
					<lat>8948248</lat>
					<long>96069816</long>
					<accuracy>4</accuracy>
					<id>38743446</id>
				</geocode>
			</city>
			<state id="16235">
				<label>CO</label>
				<geocode>
					<lat>89183111</lat>
					<long>55552990</long>
					<accuracy>8</accuracy>
					<id>60561927</id>
				</geocode>
			</state>
			<zip id="35202">
				<label>01010</label>
				<geocode>
					<lat>89908716</lat>
					<long>76055940</long>
					<accuracy>3</accuracy>
					<id>37024880</id>
				</geocode>
			</zip>
			<phone id="70458">
				<type>1</type>
				<label>home</label>
				<area>508</area>
				<prefix>315</prefix>
				<ex>3692</ex>
			</phone>

			<phone id="47746">
				<type>0</type>
				<label>home</label>
				<area>902</area>
				<prefix>479</prefix>
				<ex>2202</ex>
			</phone>

			<notes>are you hungry?</notes>
			<geocode>
				<lat>38037138</lat>
				<long>68381074</long>
				<accuracy>2</accuracy>
				<id>63798789</id>
			</geocode>
		</address>
		<phone id="24790">
			<type>0</type>
			<label>home</label>
			<area>746</area>
			<prefix>923</prefix>
			<ex>9500</ex>
		</phone>
		<email id="1944">
			<label>email</label>
			<address>Frederic@test.com</address>
			<nic>me</nic>
		</email>
		<notes>are you hungry?</notes>
	</row>
	<row>

		<person id="866">
			<first>Bill</first>
			<last>Danish</last>
			<middle>D</middle>
		</person>
		<address id="5508">
			<street1>9301 Summer Street</street1>
			<street2></street2>
			<city id="74826">
				<label>Santa Fe</label>
				<geocode>
					<lat>58270140</lat>
					<long>2261418</long>
					<accuracy>1</accuracy>
					<id>57904616</id>
				</geocode>
			</city>
			<state id="38412">
				<label>MO</label>
				<geocode>
					<lat>76348804</lat>
					<long>90398428</long>
					<accuracy>4</accuracy>
					<id>28488696</id>
				</geocode>
			</state>
			<zip id="10475">
				<label>01603</label>
				<geocode>
					<lat>73327357</lat>
					<long>75822317</long>
					<accuracy>0</accuracy>
					<id>23335152</id>
				</geocode>
			</zip>
			<phone id="60551">
				<type>1</type>
				<label>home</label>
				<area>969</area>
				<prefix>89</prefix>
				<ex>5489</ex>
			</phone>

			<phone id="23868">
				<type>1</type>
				<label>home</label>
				<area>205</area>
				<prefix>766</prefix>
				<ex>6853</ex>
			</phone>

			<notes>are you hungry?</notes>
			<geocode>
				<lat>63085282</lat>
				<long>56108779</long>
				<accuracy>6</accuracy>
				<id>14227890</id>
			</geocode>
		</address>
		<phone id="96747">
			<type>0</type>
			<label>home</label>
			<area>112</area>
			<prefix>742</prefix>
			<ex>3329</ex>
		</phone>
		<email id="40288">
			<label>email</label>
			<address>Cherry@test.com</address>
			<nic>me</nic>
		</email>
		<notes>are you hungry?</notes>
	</row>
</rowset>
